ldmud_dbus/__init__.py
ldmud_dbus-0.0.2.dist-info/LICENSE
ldmud_dbus-0.0.2.dist-info/METADATA
ldmud_dbus-0.0.2.dist-info/WHEEL
ldmud_dbus-0.0.2.dist-info/entry_points.txt
ldmud_dbus-0.0.2.dist-info/top_level.txt
ldmud_dbus-0.0.2.dist-info/RECORD
