Metadata-Version: 2.1
Name: ldmud-dbus
Version: 0.0.2
Summary: Python dbus package for LDMud
Home-page: https://github.com/ldmud/python-dbus
Author: LDMud Team
Author-email: ldmud-dev@UNItopia.DE
License: UNKNOWN
Platform: UNKNOWN
Classifier: Programming Language :: Python :: 3
Classifier: Operating System :: OS Independent
Requires-Python: >=3.5
Requires-Dist: ldmud-asyncio
